MANIFEST.in
README.rst
setup.py
data/testindicator.desktop
testindicator/VERSION
testindicator/__init__.py
testindicator/__main__.py
testindicator/application.py
testindicator/config.py
testindicator/fsmonitor.py
testindicator/indicator.py
testindicator/notifier.py
testindicator/paths.py
testindicator/testrunner.py
testindicator.egg-info/PKG-INFO
testindicator.egg-info/SOURCES.txt
testindicator.egg-info/dependency_links.txt
testindicator.egg-info/entry_points.txt
testindicator.egg-info/not-zip-safe
testindicator.egg-info/requires.txt
testindicator.egg-info/top_level.txt
testindicator/res/__init__.pyc
testindicator/res/greenlight-big.png
testindicator/res/greenlight.png
testindicator/res/redlight-big.png
testindicator/res/redlight.png
testindicator/res/traffic-lights.svg
testindicator/res/yellowlight-big.png
testindicator/res/yellowlight.png