Metadata-Version: 1.0
Name: testindicator
Version: 0.8
Summary: Don't worry about running tests - just write code
Home-page: https://github.com/logileifs/testindicator
Author: Logi Leifsson
Author-email: logileifs@gmail.com
License: UNKNOWN
Platform: UNKNOWN
